jplaceparser
